calculator/__init__.py
calculator/square.py
premaseemutils-2.0.0.data/data/my_data/data_file
premaseemutils-2.0.0.dist-info/LICENSE.txt
premaseemutils-2.0.0.dist-info/METADATA
premaseemutils-2.0.0.dist-info/WHEEL
premaseemutils-2.0.0.dist-info/entry_points.txt
premaseemutils-2.0.0.dist-info/top_level.txt
premaseemutils-2.0.0.dist-info/RECORD
